kfk/argument_extensions.py
kfk/commons.py
kfk/config.py
kfk/constants.py
kfk/kubectl_command_builder.py
kfk/kubernetes_commons.py
kfk/main.py
kfk/messages.py
kfk/option_extensions.py
kfk/setup.py
kfk/utils.py
kfk/commands/acls.py
kfk/commands/clusters.py
kfk/commands/configs.py
kfk/commands/console.py
kfk/commands/env.py
kfk/commands/main.py
kfk/commands/operator.py
kfk/commands/topics.py
kfk/commands/users.py
kfk/commands/connect/__init__.py
kfk/commands/connect/clusters.py
kfk/commands/connect/connectors.py
strimzi_kafka_cli-0.1.0a79.dist-info/LICENSE
strimzi_kafka_cli-0.1.0a79.dist-info/METADATA
strimzi_kafka_cli-0.1.0a79.dist-info/WHEEL
strimzi_kafka_cli-0.1.0a79.dist-info/entry_points.txt
strimzi_kafka_cli-0.1.0a79.dist-info/top_level.txt
strimzi_kafka_cli-0.1.0a79.dist-info/zip-safe
strimzi_kafka_cli-0.1.0a79.dist-info/RECORD
