Metadata-Version: 2.1
Name: strimzi-kafka-cli
Version: 0.1.0a79
Summary: Command Line Interface for Strimzi Kafka Operator
Author-email: Aykut Bulgu <aykut@systemcraftsman.com>
License: Apache-2.0
Keywords: kafka,strimzi,cli,operator,kubernetes,k8s,openshift,apache-kafka
Classifier: Intended Audience :: Developers
Classifier: Topic :: Software Development
Classifier: License :: OSI Approved :: Apache Software License
Classifier: Programming Language :: Python :: 3
Classifier: Programming Language :: Python :: 3.9
Classifier: Programming Language :: Python :: 3.10
Classifier: Programming Language :: Python :: 3.11
Classifier: Programming Language :: Python :: 3.12
Classifier: Programming Language :: Python :: 3.13
Classifier: Programming Language :: Python :: 3 :: Only
Classifier: Operating System :: Microsoft :: Windows
Classifier: Operating System :: POSIX :: Linux
Classifier: Operating System :: POSIX
Classifier: Operating System :: Unix
Classifier: Operating System :: MacOS
Requires-Python: <3.14,>=3.9
License-File: LICENSE
Requires-Dist: click ==8.0.4
Requires-Dist: pyyaml ==6.0.1
Requires-Dist: wget ==3.2
Requires-Dist: jproperties ==2.1.1
Requires-Dist: kubernetes ==28.1.0
Provides-Extra: dev
Requires-Dist: twine ; extra == 'dev'
Requires-Dist: flake8 ; extra == 'dev'
Requires-Dist: flake8-pyproject ; extra == 'dev'
Requires-Dist: pytest ; extra == 'dev'
Requires-Dist: wheel ; extra == 'dev'
Requires-Dist: build ; extra == 'dev'
Requires-Dist: isort ; extra == 'dev'
Requires-Dist: black ; extra == 'dev'
Requires-Dist: mypy ; extra == 'dev'
Requires-Dist: pre-commit <4 ; extra == 'dev'
Requires-Dist: bandit ; extra == 'dev'
Requires-Dist: autoflake ; extra == 'dev'
